{
	"id": "ffg-star-wars-utilities",
	"title": "FFG Star Wars - Utilities",
	"description": "Macros and some items",
	"version": "12.0.1.1_903",
	"compatibility": {
		"minimum": "12",
		"verified": "12"
	},
	"system": "starwarsffg",
	"relationships": {
		"systems": [
			{
				"id": "starwarsffg",
				"manifest": "https://raw.githubusercontent.com/StarWarsFoundryVTT/StarWarsFFG/master/system.json",
				"type": "system",
				"compatibility": {
					"minimum": "1.901",
					"verified": "1.903"
				}
			}
		],
		"requires": [
			{
				"id": "babele",
				"type": "module",
				"manifest": "https://gitlab.com/riccisi/foundryvtt-babele/raw/master/module/module.json",
				"compatibility": {
					"minimum": "2.5.0",
					"verified": "2.5.5"
				}
			},
			{
				"id": "ffg-star-wars-enhancements",
				"type": "module",
				"manifest": "https://github.com/wrycu/StarWarsFFG-Enhancements/releases/latest/download/module.json",
				"compatibility": {
					"minimum": "2.1.1",
					"verified": "2.1.1"
				}
			}
		]
	},
	"esmodules": [
		"scripts/ffg-star-wars-utilities.js"
	],
	"languages": [
		{
			"lang": "en",
			"name": "English",
			"path": "lang/en.json"
		},
		{
			"lang": "fr",
			"name": "French (Français)",
			"path": "lang/fr.json"
		}
	],
	"packs": [
		{
			"name": "utilities-items",
			"label": "Utilities - Items",
			"path": "packs/items",
			"type": "Item",
			"system": "starwarsffg",
			"ownership": {
				"PLAYER": "OBSERVER",
				"ASSISTANT": "OWNER"
			},
			"flags": {}
		},
		{
			"name": "utilities-macros",
			"label": "Utilities - Macros",
			"path": "packs/macros",
			"type": "Macro",
			"ownership": {
				"PLAYER": "OBSERVER",
				"ASSISTANT": "OWNER"
			},
			"flags": {}
		},
		{
			"name": "utilities-roll-tables",
			"label": "Utilities - Roll Tables",
			"path": "packs/roll-tables",
			"type": "RollTable",
			"ownership": {
				"PLAYER": "OBSERVER",
				"ASSISTANT": "OWNER"
			}
		}
	],
	"url": "https://github.com/TeddyBears/StarWarsFFG-utilities",
	"changelog":"https://github.com/TeddyBears/StarWarsFFG-utilities/blob/main/CHANGELOG.md",
	"readme":"https://github.com/TeddyBears/StarWarsFFG-utilities/blob/main/README.md",
	"manifest": "https://raw.githubusercontent.com/TeddyBears/StarWarsFFG-utilities/main/module.json",
	"download": "https://github.com/TeddyBears/StarWarsFFG-utilities/archive/refs/tags/v12.0.1.1_903.zip"
}